hiddifypanel/Events.py
hiddifypanel/VERSION
hiddifypanel/VERSION.py
hiddifypanel/__init__.py
hiddifypanel/__main__.py
hiddifypanel/auth.py
hiddifypanel/base.py
hiddifypanel/base_setup.py
hiddifypanel/cache.py
hiddifypanel/celery.py
hiddifypanel/database.py
hiddifypanel/apps/__init__.py
hiddifypanel/apps/asgi_app.py
hiddifypanel/apps/celery_app.py
hiddifypanel/apps/celery_app_flask.py
hiddifypanel/apps/wsgi_app.py
hiddifypanel/drivers/abstract_driver.py
hiddifypanel/drivers/singbox_api.py
hiddifypanel/drivers/ssh_liberty_bridge_api.py
hiddifypanel/drivers/user_driver.py
hiddifypanel/drivers/wireguard_api.py
hiddifypanel/drivers/xray_api.py
hiddifypanel/hutils/__init__.py
hiddifypanel/hutils/auth.py
hiddifypanel/hutils/convert.py
hiddifypanel/hutils/crypto.py
hiddifypanel/hutils/encode.py
hiddifypanel/hutils/flask.py
hiddifypanel/hutils/github_issue.py
hiddifypanel/hutils/model.py
hiddifypanel/hutils/random.py
hiddifypanel/hutils/system.py
hiddifypanel/hutils/utils.py
hiddifypanel/hutils/importer/__init__.py
hiddifypanel/hutils/importer/xui.py
hiddifypanel/hutils/network/__init__.py
hiddifypanel/hutils/network/auto_ip_selector.py
hiddifypanel/hutils/network/cf_api.py
hiddifypanel/hutils/network/net.py
hiddifypanel/hutils/node/__init__.py
hiddifypanel/hutils/node/api_client.py
hiddifypanel/hutils/node/child.py
hiddifypanel/hutils/node/parent.py
hiddifypanel/hutils/node/shared.py
hiddifypanel/hutils/proxy/__init__.py
hiddifypanel/hutils/proxy/clash.py
hiddifypanel/hutils/proxy/shared.py
hiddifypanel/hutils/proxy/singbox.py
hiddifypanel/hutils/proxy/wireguard.py
hiddifypanel/hutils/proxy/xray.py
hiddifypanel/hutils/proxy/xrayjson.py
hiddifypanel/models/__init__.py
hiddifypanel/models/admin.py
hiddifypanel/models/base_account.py
hiddifypanel/models/child.py
hiddifypanel/models/config.py
hiddifypanel/models/config_enum.py
hiddifypanel/models/domain.py
hiddifypanel/models/parent_domain.py
hiddifypanel/models/proxy.py
hiddifypanel/models/report.py
hiddifypanel-11.0.17.dist-info/licenses/LICENSE.md
hiddifypanel-11.0.17.dist-info/METADATA
hiddifypanel-11.0.17.dist-info/WHEEL
hiddifypanel-11.0.17.dist-info/entry_points.txt
hiddifypanel-11.0.17.dist-info/top_level.txt
hiddifypanel-11.0.17.dist-info/RECORD
